invenio_damap/__init__.py
invenio_damap/config.py
invenio_damap/export.py
invenio_damap/ext.py
invenio_damap/fetchers.py
invenio_damap/generators.py
invenio_damap/webpack.py
invenio_damap/assets/semantic-ui/js/invenio_damap/DMPAddButton.js
invenio_damap/assets/semantic-ui/js/invenio_damap/DMPAuthButton.js
invenio_damap/assets/semantic-ui/js/invenio_damap/DMPEntry.js
invenio_damap/assets/semantic-ui/js/invenio_damap/DMPModal.js
invenio_damap/assets/semantic-ui/js/invenio_damap/index.js
invenio_damap/resources/__init__.py
invenio_damap/resources/config.py
invenio_damap/resources/resources.py
invenio_damap/services/__init__.py
invenio_damap/services/config.py
invenio_damap/services/errors.py
invenio_damap/services/links.py
invenio_damap/services/permissions.py
invenio_damap/services/results.py
invenio_damap/services/schema.py
invenio_damap/services/services.py
invenio_damap/templates/semantic-ui/invenio_damap/damap_sidebar.html
invenio_damap/templates/semantic-ui/invenio_damap/macros/detail.html
invenio_damap/views/__init__.py
invenio_damap/views/api.py
invenio_damap/views/ui.py
invenio_damap-0.2.1.dist-info/LICENSE
invenio_damap-0.2.1.dist-info/METADATA
invenio_damap-0.2.1.dist-info/WHEEL
invenio_damap-0.2.1.dist-info/entry_points.txt
invenio_damap-0.2.1.dist-info/top_level.txt
invenio_damap-0.2.1.dist-info/RECORD
