Metadata-Version: 2.1
Name: invenio-damap
Version: 0.2.1
Summary: InvenioRDM module for the Invenio-DAMAP connection.
Home-page: https://github.com/fair-data-austria/invenio-damap
Author: DAMAP
Author-email: info@damap.org
License: MIT
Keywords: invenio rdm damap
Platform: any
Classifier: Development Status :: 5 - Production/Stable
Requires-Python: >=3.7
License-File: LICENSE
Requires-Dist: invenio-app-rdm>=12.0.0
Provides-Extra: tests
Requires-Dist: pytest-black>=0.3.0; extra == "tests"
Requires-Dist: importlib-metadata<5.0.0; extra == "tests"
Requires-Dist: invenio-app-rdm>=12.0.0; extra == "tests"
Requires-Dist: itsdangerous<2.1.0; extra == "tests"
Requires-Dist: pluggy<1.0; extra == "tests"
Requires-Dist: pytest<7.2.0; extra == "tests"
Requires-Dist: pytest-invenio<3.0.0,>=2.1.0; extra == "tests"
Requires-Dist: pytest-mock>=1.6.0; extra == "tests"
Requires-Dist: sphinx>=4.5.0; extra == "tests"
